apps/__init__.py
apps/gui/__init__.py
apps/gui/main.py
apps/gui/main_window.py
apps/gui/theme.py
apps/gui/widgets/__init__.py
apps/gui/widgets/app_matcher.py
apps/gui/widgets/battery_monitor.py
apps/gui/widgets/binding_editor.py
apps/gui/widgets/device_list.py
apps/gui/widgets/dpi_editor.py
apps/gui/widgets/hotkey_editor.py
apps/gui/widgets/macro_editor.py
apps/gui/widgets/profile_panel.py
apps/gui/widgets/razer_controls.py
apps/gui/widgets/setup_wizard.py
apps/gui/widgets/zone_editor.py
apps/gui/widgets/device_visual/__init__.py
apps/gui/widgets/device_visual/button_binding_dialog.py
apps/gui/widgets/device_visual/device_visual_widget.py
apps/tray/__init__.py
apps/tray/hotkey_backends.py
apps/tray/hotkeys.py
apps/tray/main.py
crates/__init__.py
crates/device_layouts/__init__.py
crates/device_layouts/fallback.py
crates/device_layouts/registry.py
crates/device_layouts/schema.py
crates/device_registry/__init__.py
crates/device_registry/registry.py
crates/keycode_map/__init__.py
crates/keycode_map/mapping.py
crates/profile_schema/__init__.py
crates/profile_schema/loader.py
crates/profile_schema/schema.py
crates/profile_schema/settings.py
crates/zone_definitions/__init__.py
razer_control_center-1.9.8.dist-info/licenses/LICENSE
services/__init__.py
services/app_watcher/__init__.py
services/app_watcher/watcher.py
services/macro_engine/__init__.py
services/macro_engine/player.py
services/macro_engine/recorder.py
services/openrazer_bridge/__init__.py
services/openrazer_bridge/bridge.py
services/remap_daemon/__init__.py
services/remap_daemon/daemon.py
services/remap_daemon/engine.py
services/remap_daemon/main.py
tools/__init__.py
tools/device_cli.py
tools/keymap_check.py
tools/macro_cli.py
tools/profile_cli.py
tools/debug/__init__.py
tools/debug/monitor_all.py
tools/debug/monitor_buttons.py
tools/debug/test_remap.py
razer_control_center-1.9.8.dist-info/METADATA
razer_control_center-1.9.8.dist-info/WHEEL
razer_control_center-1.9.8.dist-info/entry_points.txt
razer_control_center-1.9.8.dist-info/top_level.txt
razer_control_center-1.9.8.dist-info/RECORD
