Metadata-Version: 2.4
Name: razer-control-center
Version: 1.9.8
Summary: Razer Control Center for Linux - button remapping, macros, RGB lighting, and DPI control
Author-email: AreteDriver <aretedriver@users.noreply.github.com>
Maintainer-email: AreteDriver <aretedriver@users.noreply.github.com>
License-Expression: MIT
Project-URL: Homepage, https://github.com/AreteDriver/Razer_Controls
Project-URL: Documentation, https://github.com/AreteDriver/Razer_Controls#readme
Project-URL: Repository, https://github.com/AreteDriver/Razer_Controls.git
Project-URL: Issues, https://github.com/AreteDriver/Razer_Controls/issues
Project-URL: Changelog, https://github.com/AreteDriver/Razer_Controls/blob/main/CHANGELOG.md
Keywords: razer,linux,gaming,peripherals,rgb,macros,button-remapping,openrazer,synapse,mouse,keyboard,dpi
Classifier: Development Status :: 4 - Beta
Classifier: Environment :: X11 Applications :: Qt
Classifier: Intended Audience :: End Users/Desktop
Classifier: Operating System :: POSIX :: Linux
Classifier: Programming Language :: Python :: 3
Classifier: Programming Language :: Python :: 3.10
Classifier: Programming Language :: Python :: 3.11
Classifier: Programming Language :: Python :: 3.12
Classifier: Programming Language :: Python :: 3.13
Classifier: Topic :: Desktop Environment
Classifier: Topic :: Games/Entertainment
Classifier: Topic :: System :: Hardware
Classifier: Topic :: Utilities
Requires-Python: >=3.10
License-File: LICENSE
Requires-Dist: PySide6>=6.5.0
Requires-Dist: evdev>=1.6.0
Requires-Dist: pydbus>=0.6.0
Requires-Dist: pydantic>=2.0.0
Requires-Dist: pynput>=1.7.0
Requires-Dist: PyYAML>=6.0
Requires-Dist: PyGObject<3.50.0,>=3.42.0
Provides-Extra: dev
Requires-Dist: pytest>=7.0.0; extra == "dev"
Requires-Dist: pytest-cov>=4.0.0; extra == "dev"
Requires-Dist: pytest-asyncio>=0.21.0; extra == "dev"
Requires-Dist: ruff>=0.1.0; extra == "dev"
Requires-Dist: mypy>=1.0.0; extra == "dev"
Dynamic: license-file
